keyring_subprocess_landmark/__init__.py
keyring_subprocess_landmark-0.3.0.dist-info/entry_points.txt
keyring_subprocess_landmark-0.3.0.dist-info/WHEEL
keyring_subprocess_landmark-0.3.0.dist-info/METADATA
keyring_subprocess_landmark-0.3.0.dist-info/RECORD
